tuimoji/__init__.py
tuimoji/emojis.json
tuimoji/tuimoji.py
tuimoji-1.0.0.dist-info/METADATA
tuimoji-1.0.0.dist-info/RECORD
tuimoji-1.0.0.dist-info/WHEEL
tuimoji-1.0.0.dist-info/entry_points.txt
tuimoji-1.0.0.dist-info/top_level.txt
