Metadata-Version: 2.1
Name: tuimoji
Version: 1.0.0
Summary: A terminal ui based emoji selector.
Home-page: https://github.com/Fingel/tuimoji
Author: Austin Riba
Author-email: austin@m51.io
License: GPLv3
Project-URL: Documentation, https://github.com/Fingel/tuimoji
Project-URL: Issues, https://github.com/Fingel/tuimoji/issues
Keywords: emoji emojis console terminal
Platform: UNKNOWN
Classifier: Development Status :: 5 - Production/Stable
Classifier: Topic :: System :: Console Fonts
Classifier: Topic :: Text Processing :: Fonts
Classifier: Operating System :: Unix
Classifier: Programming Language :: Python :: 3
Classifier: License :: OSI Approved :: GNU General Public License v3 (GPLv3)
Requires-Python: >=3
Requires-Dist: urwid
